hamkit/cli/__about__.py
hamkit/cli/__init__.py
hamkit/cli/__main__.py
hamkit/__main__.py
hamkit-0.0.1a4.dist-info/METADATA
hamkit-0.0.1a4.dist-info/WHEEL
hamkit-0.0.1a4.dist-info/licenses/LICENSE
hamkit-0.0.1a4.dist-info/RECORD
