Metadata-Version: 2.3
Name: hamkit
Version: 0.0.1a4
Summary: A command-line interface for various ham radio tools.
Project-URL: Documentation, https://github.com/afourney/hamkit/blob/main/README.md
Project-URL: Issues, https://github.com/afourney/hamkit/issues
Project-URL: Source, https://github.com/afourney/hamkit/
Author-email: Adam Fourney <adam.fourney@gmail.com>
License-Expression: MIT
License-File: LICENSE
Classifier: Development Status :: 4 - Beta
Classifier: Programming Language :: Python
Classifier: Programming Language :: Python :: 3.10
Classifier: Programming Language :: Python :: 3.11
Classifier: Programming Language :: Python :: 3.12
Classifier: Programming Language :: Python :: Implementation :: CPython
Classifier: Programming Language :: Python :: Implementation :: PyPy
Requires-Python: >=3.10
Requires-Dist: hamkit-itu
Requires-Dist: hamkit-repeaterbook
Requires-Dist: hamkit-uls
